gnb/__init__.py
gnb/gene_dataloader.py
gnb/gene_name_id_mapper.py
gnb/gene_network_builder.py
gnb/neighbor_sampler.py
gnb/network_threshold_filter.py
gnb/patient_stage_mapper.py
gnb/post_detection_analyzer.py
gnb/resource_util.py
gnb-1.0.0.dist-info/LICENSE
gnb-1.0.0.dist-info/METADATA
gnb-1.0.0.dist-info/WHEEL
gnb-1.0.0.dist-info/top_level.txt
gnb-1.0.0.dist-info/RECORD
