Metadata-Version: 2.1
Name: gnb
Version: 1.0.0
Summary: A tool to build gene co-expression network using Methylation Microarrays
Home-page: https://github.com/EndlessLethe/gene-network-builder
Author: EndlessLethe
Author-email: zengsw_study@qq.com
License: UNKNOWN
Keywords: gene network graph expression
Platform: UNKNOWN
Requires-Python: >=3
Requires-Dist: numpy (>=1.19.2)
Requires-Dist: seaborn (>=0.11.0)
Requires-Dist: matplotlib (>=3.3.1)
Requires-Dist: pandas (>=0.25.3)
Requires-Dist: scipy (>=1.5.2)
Requires-Dist: gensim (>=3.8.3)
